motmot/__init__.py
motmot/_compat.py
motmot/_curvatures.py
motmot/_mesh.py
motmot/_misc.py
motmot/_polygon_map.py
motmot/_polygon_walk.py
motmot/_queue.py
motmot/_slug.py
motmot/_version.py
motmot/connectivity.py
motmot/hook-motmot.py
motmot/motmot-Windows-32bit.dll
motmot/motmot.json
motmot/geometry/__init__.py
motmot/geometry/_geometry.py
motmot/geometry/_unit_vector.py
motmot/geometry/_unit_vector.pyi
motmot-0.3.2.dist-info/LICENSE
motmot-0.3.2.dist-info/METADATA
motmot-0.3.2.dist-info/WHEEL
motmot-0.3.2.dist-info/entry_points.txt
motmot-0.3.2.dist-info/top_level.txt
motmot-0.3.2.dist-info/RECORD
