Metadata-Version: 2.1
Name: motmot
Version: 0.3.2
Summary: A sophisticated mesh class for analysing 3D surfaces.
Home-page: https://github.com/bwoodsend/motmot
Author: Brénainn Woodsend
Author-email: bwoodsend@gmail.com
License: MIT license
Keywords: motmot
Classifier: Intended Audience :: Developers
Classifier: License :: OSI Approved :: MIT License
Classifier: Natural Language :: English
Classifier: Programming Language :: Python :: 3
Classifier: Programming Language :: Python :: 3.7
Classifier: Programming Language :: Python :: 3.8
Classifier: Programming Language :: Python :: 3.9
Classifier: Programming Language :: Python :: 3.10
Requires-Python: >=3.7
Provides-Extra: test
License-File: LICENSE
